ko_poetry_audit_plugin/__init__.py
ko_poetry_audit_plugin/auditor.py
ko_poetry_audit_plugin/command.py
ko_poetry_audit_plugin/packages.py
ko_poetry_audit_plugin/plugins.py
ko_poetry_audit_plugin/py.typed
ko_poetry_audit_plugin/pypi_warehouse.py
ko_poetry_audit_plugin/vulnerabilities.py
ko_poetry_audit_plugin-0.7.0.dist-info/entry_points.txt
ko_poetry_audit_plugin-0.7.0.dist-info/METADATA
ko_poetry_audit_plugin-0.7.0.dist-info/WHEEL
ko_poetry_audit_plugin-0.7.0.dist-info/LICENSE
ko_poetry_audit_plugin-0.7.0.dist-info/RECORD
