Metadata-Version: 2.1
Name: ko-poetry-audit-plugin
Version: 0.7.0
Summary: Poetry plugin to check known vulnerabilities from poetry.lock
License: Apache-2.0
Author: YEUNG King On
Author-email: koyeung@gmail.com
Requires-Python: >=3.9,<4.0
Classifier: License :: OSI Approved :: Apache Software License
Classifier: Programming Language :: Python :: 3
Classifier: Programming Language :: Python :: 3.9
Classifier: Programming Language :: Python :: 3.10
Classifier: Programming Language :: Python :: 3.11
Requires-Dist: httpx[http2] (>=0.23.0,<0.24.0)
Requires-Dist: poetry (>=1.2.2,<2.0.0)
Requires-Dist: tabulate (>=0.9.0,<0.10.0)
